[
  {
    "file": "2026-2-22-agent-skills.html",
    "title": "一、Skills",
    "date": "2026-2-22",
    "description": "",
    "category": "技术笔记",
    "cover": "article/image.png"
  },
  {
    "file": "2025-07-07-扫码登录的原理.html",
    "title": "2025-07-07-扫码登录的原理",
    "date": "2025-07-07",
    "description": "",
    "category": "技术笔记",
    "cover": ""
  },
  {
    "file": "2025-06-01-pickle.md",
    "title": "pickle",
    "date": "2025-06-01",
    "description": "pickle 是相当于一个指令解释器，解析对应的opcode指令。因此其实python的序列化和反序列化机制更像是一个代码执行。pickle 的反序列化器是一个 opcode 解释器：它按顺序读取 opcode 并执行对应的动作。Pickle 的 opcode ≈ Python 对象操作的汇编代码，",
    "category": "编程语言",
    "cover": "https://raw.githubusercontent.com/k1t0111/blog/main/image/20250601233737.png"
  },
  {
    "file": "2025-04-05-c--内存机制和安全.md",
    "title": "c++内存机制和安全",
    "date": "2025-04-05",
    "description": "浅拷贝是两个对象但是共用一个内存 ，深拷贝是两个对象两个内存",
    "category": "编程语言",
    "cover": ""
  },
  {
    "file": "2025-02-05-URLDNS链.md",
    "title": "URLDNS链",
    "date": "2025-02-05",
    "description": "Map是一个集合，本质上还是数组，HashMap是Map的子接口。该集合的结构为key–>value，两个一起称为一个Entry(jdk7)，在jdk8中底层的数组为Node[]。当new HashMap()时，在jdk7中会直接创建一个长度为16的数组；jdk8中并不直接创建，而是在调用put方法",
    "category": "编程语言",
    "cover": "https://raw.githubusercontent.com/k1t0111/blog/main/image/20241022213631.png"
  },
  {
    "file": "2025-02-05-java动态代理.md",
    "title": "java动态代理",
    "date": "2025-02-05",
    "description": "有一个师傅的文章讲的很好，我们经常说代理。我们可以把我们比作一个租房的人，我们找代理中介去找拥有房源的房东租房子。这个中介就可以作为一个代理。",
    "category": "编程语言",
    "cover": ""
  },
  {
    "file": "2025-02-05-java反射.md",
    "title": "java反射",
    "date": "2025-02-05",
    "description": "反射机制是 Java 提供的一种强大功能，允许程序在运行时查询和操作类的信息",
    "category": "编程语言",
    "cover": ""
  },
  {
    "file": "2025-02-05-java反序列化.md",
    "title": "java反序列化",
    "date": "2025-02-05",
    "description": "反序列化目的",
    "category": "编程语言",
    "cover": "https://raw.githubusercontent.com/k1t0111/blog/main/image/20241021201353.png"
  },
  {
    "file": "2025-02-03-红日1.md",
    "title": "红日1",
    "date": "2025-02-03",
    "description": "",
    "category": "内网渗透",
    "cover": "https://raw.githubusercontent.com/k1t0111/blog/main/image/20241012204654.png"
  },
  {
    "file": "2025-02-01-docker.md",
    "title": "docker",
    "date": "2025-02-01",
    "description": "Docker 就像一个盒子，里面可以装很多物件，如果需要某些物件，可以直接将该盒子拿走，而不需要从该盒子中一件一件的取。",
    "category": "技术笔记",
    "cover": ""
  },
  {
    "file": "2025-01-30-域常见信息枚举.md",
    "title": "域常见信息枚举",
    "date": "2025-01-30",
    "description": "当您可能无法访问系统的 RDP、防御者正在监控 PowerShell 的使用以及您需要通过远程访问木马 （RAT） 执行 AD 枚举时，可靠可靠的 CMD 非常方便。在网络钓鱼有效负载中嵌入几个简单的 AD 枚举命令甚至会有所帮助，以帮助您获取可以帮助您进行最终攻击的重要信息。",
    "category": "内网渗透",
    "cover": ""
  },
  {
    "file": "2025-01-29-SMB445端口利用.md",
    "title": "SMB445端口利用",
    "date": "2025-01-29",
    "description": "SMB协议是一种在局域网上共享文件、打印机、串行端口等资源的网络通信协议。它最初由IBM开发，后来被微软广泛采用，并成为Windows操作系统中文件共享的基础协议之一。SMB协议通常在TCP/IP网络上运行，使用TCP端口445进行通信。",
    "category": "内网渗透",
    "cover": "article/Pasted%20image%2020240415213256.png"
  },
  {
    "file": "2025-01-29-内网横向的一些方式.md",
    "title": "内网横向的一些方式",
    "date": "2025-01-29",
    "description": "多年来，Psexec 一直是需要远程执行进程时的首选方法。它允许管理员用户在他有权访问的任何 PC 上远程运行命令。 Psexec 是众多 Sysinternals 工具之一，可以在此处下载。",
    "category": "内网渗透",
    "cover": "https://tryhackme-images.s3.amazonaws.com/user-uploads/5ed5961c6276df568891c3ea/room-content/a488102fe0da47a3667961400cf298d8.png"
  },
  {
    "file": "2025-01-27-域整理-基础.md",
    "title": "域整理-基础",
    "date": "2025-01-27",
    "description": "Microsoft 的Active Directory 是企业界的支柱。它简化了企业环境中设备和用户的管理",
    "category": "内网渗透",
    "cover": ""
  },
  {
    "file": "2025-01-19-一次混淆webshell分析.md",
    "title": "一次混淆webshell分析",
    "date": "2025-01-19",
    "description": "唯一一个无法确定的就是preg_match中的$m变量。一般来讲，这就是保存捕获的字符串。",
    "category": "Web安全",
    "cover": "https://raw.githubusercontent.com/k1t0111/blog/main/image/20250119142523.png"
  },
  {
    "file": "2025-01-17-ew-内网.md",
    "title": "ew-内网",
    "date": "2025-01-17",
    "description": "我认为他的使用场景讲的已经是非常详细了",
    "category": "内网渗透",
    "cover": "https://raw.githubusercontent.com/k1t0111/blog/main/image/20250117223656.png"
  },
  {
    "file": "2025-01-15-jsonp.md",
    "title": "jsonp",
    "date": "2025-01-15",
    "description": "jsonp是一种协议，准确的说，他是json的一种使用模式，为了解决Json受同源策略限制的问题是一种使用JSON格式数据的跨域请求方式。其主要目的是绕过同源策略限制，使得网页可以通过<script>标签从不同源的服务器加载数据。主要还是利用同源策略中script 标签的src属性可以加载外部的js",
    "category": "Web安全",
    "cover": ""
  },
  {
    "file": "2025-01-15-同源策略.md",
    "title": "同源策略",
    "date": "2025-01-15",
    "description": "同源策略 (Same Origin Policy)",
    "category": "Web安全",
    "cover": ""
  },
  {
    "file": "2025-01-14-phpmyadmin-getshell姿势.md",
    "title": "phpmyadmin-getshell姿势",
    "date": "2025-01-14",
    "description": "phpMyAdmin 是一个用 PHP 编写的开源工具，旨在通过 Web 界面管理 MySQL 和 MariaDB 数据库。",
    "category": "Web安全",
    "cover": "https://raw.githubusercontent.com/k1t0111/blog/main/image/20250113162904.png"
  },
  {
    "file": "2025-01-14-内网穿透-ligolo使用.md",
    "title": "内网穿透-ligolo使用",
    "date": "2025-01-14",
    "description": "本地转发通过参数 -L 指定，格式：-L [本地主机:]本地主机端口:远程网络主机:远程网络主机端口。加上ssh待登录主机，这里就有了三台主机。",
    "category": "内网渗透",
    "cover": ""
  },
  {
    "file": "2025-01-14-内网穿透-ssh搭建.md",
    "title": "内网穿透-ssh搭建",
    "date": "2025-01-14",
    "description": "大概看懂了ligolo的操作，首先我们在进行代理的时候要么使用单独使用ssh或者要么使用ssh搭配putty进行内网穿透。要么使用frp进行穿透。但是ssh有一定的局限性，如果说我们遇到了ssh不存在的情况，就无法使用。于是我发现ligolo其实是一个利用了cs之间的连接去代替了ssh连接。同时也是",
    "category": "内网渗透",
    "cover": ""
  },
  {
    "file": "2024-11-30-RCE绕过.md",
    "title": "RCE绕过",
    "date": "2024-11-30",
    "description": "清理应用程序使用的用户输入是防止命令注入的好方法。这是指定用户可以提交的数据的格式或类型的过程。例如，仅接受数值数据或删除任何特殊字符（如 > 和 & / ）的输入字段。读取flag时候可以  不进行目录穿越  可以直接cat  /f*   (*不能被禁止)",
    "category": "Web安全",
    "cover": "https://raw.githubusercontent.com/k1t0111/blog/main/image/20241108142728.png"
  },
  {
    "file": "2024-11-12-操作系统启动实验.md",
    "title": "操作系统启动实验",
    "date": "2024-11-12",
    "description": "利用工具构建makefile",
    "category": "技术笔记",
    "cover": "https://raw.githubusercontent.com/k1t0111/blog/main/image/20241105145924.png"
  },
  {
    "file": "2024-11-12-操作系统进程管理实验.md",
    "title": "操作系统进程管理实验",
    "date": "2024-11-12",
    "description": "用系统调用fork()函数实现子进程的创建，熟悉进程创建的执行过程。",
    "category": "技术笔记",
    "cover": "https://raw.githubusercontent.com/k1t0111/blog/main/image/20241112143931.png"
  },
  {
    "file": "2024-11-05-dns欺骗.md",
    "title": "dns欺骗",
    "date": "2024-11-05",
    "description": "[[Ettercap]] 少不了这个 arp 毒化和流量截取的中间人工具。",
    "category": "内网渗透",
    "cover": "https://raw.githubusercontent.com/k1t0111/blog/main/image/20241105202402.png"
  },
  {
    "file": "2024-11-05-mac-泛洪.md",
    "title": "mac_泛洪",
    "date": "2024-11-05",
    "description": "TCP SYN Flood：",
    "category": "Web安全",
    "cover": "https://raw.githubusercontent.com/k1t0111/blog/main/image/20241104202636.png"
  },
  {
    "file": "2024-11-04-子域名泛解析解析.md",
    "title": "子域名泛解析解析",
    "date": "2024-11-04",
    "description": "  在子域名解析中，每个子域名都会解析为一个特定的IP地址。只有被设置解析，用户才能正常进行访问。  一旦用户输入错误的子域名，就会造成无法访问。  在网站运营中，域名持有者为了避免因为错误输入，而造成用户流失，就会使用泛域名解析。  泛域名解析是一种特殊的域名解析方式。它使用通配符形式，设置域名解",
    "category": "Web安全",
    "cover": "https://img2022.cnblogs.com/blog/1090320/202203/1090320-20220303113103812-1435020700.png"
  },
  {
    "file": "2024-09-18-文件上传-php.md",
    "title": "文件上传-php",
    "date": "2024-09-18",
    "description": "",
    "category": "Web安全",
    "cover": "https://raw.githubusercontent.com/k1t0111/blog/main/image/20240611204655.png"
  },
  {
    "file": "2024-09-16-CORS-跨域资源共享.md",
    "title": "CORS_跨域资源共享",
    "date": "2024-09-16",
    "description": "参考文章:",
    "category": "Web安全",
    "cover": "https://raw.githubusercontent.com/k1t0111/blog/main/image/20240916210256.png"
  },
  {
    "file": "2024-09-12-CTF-Ciscn-cyberpunk.md",
    "title": "CTF-Ciscn-cyberpunk",
    "date": "2024-09-12",
    "description": "",
    "category": "CTF",
    "cover": "https://raw.githubusercontent.com/k1t0111/blog/main/image/20240911104335.png"
  },
  {
    "file": "2024-09-10-横向移动-WMI.md",
    "title": "横向移动-WMI",
    "date": "2024-09-10",
    "description": "WMI是基于 Web 的企业管理 (WBEM) 的 Windows 实现，WBEM 是跨设备访问管理信息的企业标准。WBEM（Web-Based Enterprise Management）是一个开放标准，用于跨平台和跨设备的管理信息访问。WMI（Windows Management Instrum",
    "category": "内网渗透",
    "cover": "https://raw.githubusercontent.com/k1t0111/blog/main/image/20240910195837.png"
  },
  {
    "file": "2024-09-09-浏览器解码顺序和解析顺序for-xss.md",
    "title": "浏览器解码顺序和解析顺序for-xss",
    "date": "2024-09-09",
    "description": "首先要了解我们在构造xss包的时候发生了什么：",
    "category": "Web安全",
    "cover": "https://ask.qcloudimg.com/http-save/yehe-6367947/k8plxaz0ag.jpeg"
  },
  {
    "file": "2024-09-08-AD域枚举信息-BloodHound.md",
    "title": "AD域枚举信息-BloodHound",
    "date": "2024-09-08",
    "description": "最后，我们将研究使用Bloodhound执行 AD 枚举。 Bloodhound 是迄今为止最强大的AD枚举工具，当它于 2016 年发布时，它永远改变了AD枚举格局。",
    "category": "内网渗透",
    "cover": "https://raw.githubusercontent.com/k1t0111/blog/main/image/20240831103147.png"
  },
  {
    "file": "2024-09-08-AD域枚举信息-Microsoft控制台MMC.md",
    "title": "AD域枚举信息-Microsoft控制台MMC",
    "date": "2024-09-08",
    "description": "我们将使用 Microsoft 管理控制台 （MMC） 和远程服务器管理工具 （RSAT） AD 管理单元。如果您使用提供的 Windows VM （THMJMP1），则已为您安装该 VM。但是，如果您使用的是自己的 Windows 计算机，则可以执行以下步骤来安装管理单元：",
    "category": "内网渗透",
    "cover": "https://raw.githubusercontent.com/k1t0111/blog/main/image/20240907200746.png"
  },
  {
    "file": "2024-09-08-AD域枚举信息-powershell-cmdlet.md",
    "title": "AD域枚举信息-powershell-cmdlet",
    "date": "2024-09-08",
    "description": "安装 Active Directory 远程管理工具（AD-RSAT，Active Directory Remote Server Administration Tools）后，系统会自动安装一组用于管理 Active Directory 的 PowerShell cmdlet。这些 cmdlet ",
    "category": "内网渗透",
    "cover": "https://raw.githubusercontent.com/k1t0111/blog/main/image/20240830201932.png"
  },
  {
    "file": "2024-09-08-AD域枚举信息-命令枚举.md",
    "title": "AD域枚举信息-命令枚举",
    "date": "2024-09-08",
    "description": "有时，您只需要执行快速而肮脏的AD查找，而命令提示符会为您提供支持。当您可能无法访问系统的 RDP、防御者正在监控 PowerShell 的使用以及您需要通过远程访问木马 （RAT） 执行 AD 枚举时，可靠可靠的 CMD 非常方便。在网络钓鱼有效负载中嵌入几个简单的 AD 枚举命令甚至会有所帮助，",
    "category": "内网渗透",
    "cover": ""
  },
  {
    "file": "2024-09-08-横向移动-远程创建进程.md",
    "title": "横向移动-远程创建进程",
    "date": "2024-09-08",
    "description": "多年来，Psexec 一直是需要远程执行进程时的首选方法。它允许管理员用户在他有权访问的任何 PC 上远程运行命令。 Psexec 是众多 Sysinternals 工具之一，可以在此处下载。",
    "category": "内网渗透",
    "cover": "https://tryhackme-images.s3.amazonaws.com/user-uploads/5ed5961c6276df568891c3ea/room-content/a488102fe0da47a3667961400cf298d8.png"
  },
  {
    "file": "2024-08-17-log4shell.md",
    "title": "log4shell",
    "date": "2024-08-17",
    "description": "Apache log4j是Apache的一个开源项目，Apache log4j 2是一个就Java的日志记录工具。通过重写了log4j框架，并且引入了大量丰富的特性，可以控制日志信息输送的目的地为控制台、文件、GUI组建等，被应用于业务系统开发，用于记录程序输入输出日志信息。log4j2中存在JND",
    "category": "Web安全",
    "cover": "https://raw.githubusercontent.com/k1t0111/blog/main/image/20240806105256.png"
  },
  {
    "file": "2024-07-21-ctfhub-ssrf基础认证.md",
    "title": "ctfhub_ssrf基础认证",
    "date": "2024-07-21",
    "description": "",
    "category": "CTF",
    "cover": "https://raw.githubusercontent.com/k1t0111/blog/main/image/20240721162712.png"
  },
  {
    "file": "2024-07-21-redis-利用方式大全.md",
    "title": "redis_利用方式大全",
    "date": "2024-07-21",
    "description": "",
    "category": "Web安全",
    "cover": "https://raw.githubusercontent.com/k1t0111/blog/main/image/20240721160632.png"
  },
  {
    "file": "2024-04-25-HTB-LAME.md",
    "title": "HTB-LAME",
    "date": "2024-04-25",
    "description": "强扫描一下ftp",
    "category": "靶场实践",
    "cover": ""
  },
  {
    "file": "2024-03-30-ctf-misc-掌控腾龙杯.md",
    "title": "ctf-misc-掌控腾龙杯",
    "date": "2024-03-30",
    "description": "在stegsolve中把msb中的rgb三个颜色拉满就会出现",
    "category": "CTF",
    "cover": "https://img2.imgtp.com/2024/03/28/cB0lrjpx.png"
  },
  {
    "file": "2024-03-19-权限提升-windows服务提权.md",
    "title": "权限提升-windows服务提权",
    "date": "2024-03-19",
    "description": "  Windows 服务由服务控制管理器 (SCM) 管理。 SCM 是一个负责根据需要管理服务状态、检查任何给定服务的当前状态并通常提供配置服务的方法的进程。",
    "category": "内网渗透",
    "cover": "https://img2.imgtp.com/2024/03/18/1mRaN220.png"
  },
  {
    "file": "2024-03-09-权限提升-windows计划任务提权.md",
    "title": "权限提升-windows计划任务提权",
    "date": "2024-03-09",
    "description": "探索者安全团队技术文章仅供参考,未经授权请勿利用文章中的技术资料对任何计算机系统进行入侵操作,由于传播、利用本公众号所提供的技术和信息而造成的任何直接或者间接的后果及损失，均由使用者本人负责，作者不为此承担任何责任,如有侵权烦请告知，我们会立即删除并致歉,创作不易转载请标明出处.感谢!",
    "category": "内网渗透",
    "cover": "https://img2.imgtp.com/2024/03/09/6XYOTwOf.png"
  },
  {
    "file": "2024-03-04-权限提升-Linux-passwd提权.md",
    "title": "权限提升-Linux passwd提权",
    "date": "2024-03-04",
    "description": "",
    "category": "内网渗透",
    "cover": "https://files.catbox.moe/ycbdfb.png"
  }
]